{"$":"Function","jQuery":"Function","_":"Function","_.VERSION":"String","_.iteratee":"Function","_.forEach":"Function","_.each":"Function","_.collect":"Function","_.map":"Function","_.inject":"Function","_.foldl":"Function","_.reduce":"Function","_.foldr":"Function","_.reduceRight":"Function","_.detect":"Function","_.find":"Function","_.select":"Function","_.filter":"Function","_.reject":"Function","_.all":"Function","_.every":"Function","_.any":"Function","_.some":"Function","_.include":"Function","_.includes":"Function","_.contains":"Function","_.invoke":"Function","_.pluck":"Function","_.where":"Function","_.findWhere":"Function","_.max":"Function","_.min":"Function","_.shuffle":"Function","_.sample":"Function","_.sortBy":"Function","_.groupBy":"Function","_.indexBy":"Function","_.countBy":"Function","_.toArray":"Function","_.size":"Function","_.partition":"Function","_.take":"Function","_.head":"Function","_.first":"Function","_.initial":"Function","_.last":"Function","_.drop":"Function","_.tail":"Function","_.rest":"Function","_.compact":"Function","_.flatten":"Function","_.without":"Function","_.unique":"Function","_.uniq":"Function","_.union":"Function","_.intersection":"Function","_.difference":"Function","_.zip":"Function","_.unzip":"Function","_.object":"Function","_.findIndex":"Function","_.findLastIndex":"Function","_.sortedIndex":"Function","_.indexOf":"Function","_.lastIndexOf":"Function","_.range":"Function","_.bind":"Function","_.partial":"Function","_.bindAll":"Function","_.memoize":"Function","_.delay":"Function","_.defer":"Function","_.throttle":"Function","_.debounce":"Function","_.wrap":"Function","_.negate":"Function","_.compose":"Function","_.after":"Function","_.before":"Function","_.once":"Function","_.keys":"Function","_.allKeys":"Function","_.values":"Function","_.mapObject":"Function","_.pairs":"Function","_.invert":"Function","_.methods":"Function","_.functions":"Function","_.extend":"Function","_.assign":"Function","_.extendOwn":"Function","_.findKey":"Function","_.pick":"Function","_.omit":"Function","_.defaults":"Function","_.create":"Function","_.clone":"Function","_.tap":"Function","_.isMatch":"Function","_.isEqual":"Function","_.isEmpty":"Function","_.isElement":"Function","_.isArray":"Function","_.isObject":"Function","_.isArguments":"Function","_.isFunction":"Function","_.isString":"Function","_.isNumber":"Function","_.isDate":"Function","_.isRegExp":"Function","_.isError":"Function","_.isFinite":"Function","_.isNaN":"Function","_.isBoolean":"Function","_.isNull":"Function","_.isUndefined":"Function","_.has":"Function","_.noConflict":"Function","_.identity":"Function","_.constant":"Function","_.noop":"Function","_.property":"Function","_.propertyOf":"Function","_.matches":"Function","_.matcher":"Function","_.times":"Function","_.random":"Function","_.now":"Function","_.escape":"Function","_.unescape":"Function","_.result":"Function","_.uniqueId":"Function","_.templateSettings.evaluate":"RegExp","_.templateSettings.interpolate":"RegExp","_.templateSettings.escape":"RegExp","_.templateSettings":"object","_.template":"Function","_.chain":"Function","_.mixin":"Function","_.prototype.after":"Function","_.prototype.all":"Function","_.prototype.allKeys":"Function","_.prototype.any":"Function","_.prototype.assign":"Function","_.prototype.before":"Function","_.prototype.bind":"Function","_.prototype.bindAll":"Function","_.prototype.chain":"Function","_.prototype.clone":"Function","_.prototype.collect":"Function","_.prototype.compact":"Function","_.prototype.compose":"Function","_.prototype.constant":"Function","_.prototype.contains":"Function","_.prototype.countBy":"Function","_.prototype.create":"Function","_.prototype.debounce":"Function","_.prototype.defaults":"Function","_.prototype.defer":"Function","_.prototype.delay":"Function","_.prototype.detect":"Function","_.prototype.difference":"Function","_.prototype.drop":"Function","_.prototype.each":"Function","_.prototype.escape":"Function","_.prototype.every":"Function","_.prototype.extend":"Function","_.prototype.extendOwn":"Function","_.prototype.filter":"Function","_.prototype.find":"Function","_.prototype.findIndex":"Function","_.prototype.findKey":"Function","_.prototype.findLastIndex":"Function","_.prototype.findWhere":"Function","_.prototype.first":"Function","_.prototype.flatten":"Function","_.prototype.foldl":"Function","_.prototype.foldr":"Function","_.prototype.forEach":"Function","_.prototype.functions":"Function","_.prototype.groupBy":"Function","_.prototype.has":"Function","_.prototype.head":"Function","_.prototype.identity":"Function","_.prototype.include":"Function","_.prototype.includes":"Function","_.prototype.indexBy":"Function","_.prototype.indexOf":"Function","_.prototype.initial":"Function","_.prototype.inject":"Function","_.prototype.intersection":"Function","_.prototype.invert":"Function","_.prototype.invoke":"Function","_.prototype.isArguments":"Function","_.prototype.isArray":"Function","_.prototype.isBoolean":"Function","_.prototype.isDate":"Function","_.prototype.isElement":"Function","_.prototype.isEmpty":"Function","_.prototype.isEqual":"Function","_.prototype.isError":"Function","_.prototype.isFinite":"Function","_.prototype.isFunction":"Function","_.prototype.isMatch":"Function","_.prototype.isNaN":"Function","_.prototype.isNull":"Function","_.prototype.isNumber":"Function","_.prototype.isObject":"Function","_.prototype.isRegExp":"Function","_.prototype.isString":"Function","_.prototype.isUndefined":"Function","_.prototype.iteratee":"Function","_.prototype.keys":"Function","_.prototype.last":"Function","_.prototype.lastIndexOf":"Function","_.prototype.map":"Function","_.prototype.mapObject":"Function","_.prototype.matcher":"Function","_.prototype.matches":"Function","_.prototype.max":"Function","_.prototype.memoize":"Function","_.prototype.methods":"Function","_.prototype.min":"Function","_.prototype.mixin":"Function","_.prototype.negate":"Function","_.prototype.noConflict":"Function","_.prototype.noop":"Function","_.prototype.now":"Function","_.prototype.object":"Function","_.prototype.omit":"Function","_.prototype.once":"Function","_.prototype.pairs":"Function","_.prototype.partial":"Function","_.prototype.partition":"Function","_.prototype.pick":"Function","_.prototype.pluck":"Function","_.prototype.property":"Function","_.prototype.propertyOf":"Function","_.prototype.random":"Function","_.prototype.range":"Function","_.prototype.reduce":"Function","_.prototype.reduceRight":"Function","_.prototype.reject":"Function","_.prototype.rest":"Function","_.prototype.result":"Function","_.prototype.sample":"Function","_.prototype.select":"Function","_.prototype.shuffle":"Function","_.prototype.size":"Function","_.prototype.some":"Function","_.prototype.sortBy":"Function","_.prototype.sortedIndex":"Function","_.prototype.tail":"Function","_.prototype.take":"Function","_.prototype.tap":"Function","_.prototype.template":"Function","_.prototype.throttle":"Function","_.prototype.times":"Function","_.prototype.toArray":"Function","_.prototype.unescape":"Function","_.prototype.union":"Function","_.prototype.uniq":"Function","_.prototype.unique":"Function","_.prototype.uniqueId":"Function","_.prototype.unzip":"Function","_.prototype.values":"Function","_.prototype.where":"Function","_.prototype.without":"Function","_.prototype.wrap":"Function","_.prototype.zip":"Function","_.prototype.pop":"Function","_.prototype.push":"Function","_.prototype.reverse":"Function","_.prototype.shift":"Function","_.prototype.sort":"Function","_.prototype.splice":"Function","_.prototype.unshift":"Function","_.prototype.concat":"Function","_.prototype.join":"Function","_.prototype.slice":"Function","_.prototype.value":"Function","_.prototype.toJSON":"Function","_.prototype.valueOf":"Function","_.prototype.toString":"Function","$.isReady":"Boolean","jQuery.isReady":"Boolean","$.readyWait":"Number","jQuery.readyWait":"Number"}